mapyr/__init__.py
mapyr/core.py
mapyr/exceptions.py
mapyr/langmods/c.py
mapyr/langmods/python.py
mapyr/logs.py
mapyr/utils.py
mapyr-0.9.1.dist-info/METADATA
mapyr-0.9.1.dist-info/WHEEL
mapyr-0.9.1.dist-info/RECORD
